fingest/__init__.py
fingest/plugin.py
fingest/types.py
fingest-0.1.0.dist-info/LICENSE
fingest-0.1.0.dist-info/METADATA
fingest-0.1.0.dist-info/WHEEL
fingest-0.1.0.dist-info/entry_points.txt
fingest-0.1.0.dist-info/RECORD
