Metadata-Version: 2.3
Name: fingest
Version: 0.1.0
Summary: Pytest plugin that allows you to easily define data-driven fixtures based on external files.
License: MIT
Keywords: pytest,plugin,fixtures,data-driven,testing,json,csv,xml
Author: Tim Fiedler
Author-email: tim@0x68.de
Requires-Python: >=3.11
Classifier: Development Status :: 4 - Beta
Classifier: Framework :: Pytest
Classifier: Intended Audience :: Developers
Classifier: License :: OSI Approved :: MIT License
Classifier: Programming Language :: Python :: 3
Classifier: Programming Language :: Python :: 3.11
Classifier: Programming Language :: Python :: 3.12
Classifier: Programming Language :: Python :: 3.13
Classifier: Topic :: Software Development :: Libraries :: Python Modules
Classifier: Topic :: Software Development :: Testing
Requires-Dist: lxml (>=5.4.0,<6.0.0)
Requires-Dist: pytest (>=8.3.5,<9.0.0)
Project-URL: Documentation, https://github.com/0x68/fingest#readme
Project-URL: Homepage, https://github.com/0x68/fingest
Project-URL: Issues, https://github.com/0x68/fingest/issues
Project-URL: Repository, https://github.com/0x68/fingest
